requests_hardened/__init__.py
requests_hardened/client.py
requests_hardened/config.py
requests_hardened/ip_filter.py
requests_hardened/ip_filter_adapter.py
requests_hardened/manager.py
requests_hardened/types.py
requests_hardened-1.2.0.dist-info/METADATA
requests_hardened-1.2.0.dist-info/WHEEL
requests_hardened-1.2.0.dist-info/licenses/LICENSE
requests_hardened-1.2.0.dist-info/RECORD
